redbuild/__init__.py
redbuild/__main__.py
redbuild/cli.py
redbuild/composer.py
redbuild/engine.py
redbuild/res.py
redbuild/util.py
redbuild-2.3.0.dist-info/LICENSE
redbuild-2.3.0.dist-info/METADATA
redbuild-2.3.0.dist-info/WHEEL
redbuild-2.3.0.dist-info/entry_points.txt
redbuild-2.3.0.dist-info/RECORD
