Metadata-Version: 2.3
Name: redbuild
Version: 2.3.0
Summary: magic containerized builds
Author: redthing1
Author-email: redthing1@alt.icu
Requires-Python: >=3.9,<4.0
Classifier: Programming Language :: Python :: 3
Classifier: Programming Language :: Python :: 3.9
Classifier: Programming Language :: Python :: 3.10
Classifier: Programming Language :: Python :: 3.11
Classifier: Programming Language :: Python :: 3.12
Classifier: Programming Language :: Python :: 3.13
Requires-Dist: loguru (>=0.7.0,<0.8.0)
Requires-Dist: minlog (>=0.6.0,<0.7.0)
Requires-Dist: ordered-set (>=4.1.0,<5.0.0)
Requires-Dist: psutil (>=5.9.4,<6.0.0)
Requires-Dist: rich (>=13.3.4,<14.0.0)
Requires-Dist: sh (>=2.2.2,<3.0.0)
Requires-Dist: single-source (>=0.3.0,<0.4.0)
Requires-Dist: toml (>=0.10.2,<0.11.0)
Requires-Dist: typer (>=0.15.2,<0.16.0)
